libwampli/__init__.py
libwampli/args.py
libwampli/config.py
libwampli/context.py
libwampli/format.py
wampli/__init__.py
wampli/__main__.py
wampli/cli.py
wampli/shell.py
wampli-0.3.1.dist-info/LICENSE
wampli-0.3.1.dist-info/METADATA
wampli-0.3.1.dist-info/WHEEL
wampli-0.3.1.dist-info/entry_points.txt
wampli-0.3.1.dist-info/top_level.txt
wampli-0.3.1.dist-info/RECORD
