Metadata-Version: 2.1
Name: wampli
Version: 0.3.1
Summary: UNKNOWN
Home-page: https://github.com/gieseladev/wampli
Author: Giesela Inc.
Author-email: team@giesela.dev
License: MIT
Platform: UNKNOWN
Requires-Python: ~=3.7
Requires-Dist: aiowamp
Requires-Dist: konfi
Requires-Dist: pyyaml
